LICENSE
MANIFEST.in
README.md
setup.cfg
setup.py
examples/cifar_generator_cnn.py
examples/cnn_lstm.py
examples/complex.py
examples/hyperas_in_intermediate_fns.py
examples/lstm.py
examples/mnist_distributed.py
examples/mnist_ensemble.py
examples/mnist_readme.py
examples/simple.py
examples/simple_notebook.ipynb
examples/simple_notebook_multiple_inputs.ipynb
examples/use_intermediate_functions.py
hellohyperas/__init__.py
hellohyperas/distributions.py
hellohyperas/ensemble.py
hellohyperas/optim.py
hellohyperas/utils.py
hellohyperas.egg-info/PKG-INFO
hellohyperas.egg-info/SOURCES.txt
hellohyperas.egg-info/dependency_links.txt
hellohyperas.egg-info/not-zip-safe
hellohyperas.egg-info/requires.txt
hellohyperas.egg-info/top_level.txt
tests/test_distributions.py
tests/test_e2e.py
tests/test_ensemble.py
tests/test_functional_api.py
tests/test_lr_plateau.py
tests/test_optim.py
tests/test_utils.py