Metadata-Version: 1.1
Name: hellohyperas
Version: 1.0.0
Summary: custom notebook filepath enabled, hyperas 0.4.1
Home-page: http://github.com/maxpumperla/hyperas
Author: Max Pumperla
Author-email: max.pumperla@googlemail.com
License: MIT
Download-URL: https://github.com/maxpumperla/hyperas/tarball/0.4.1
Platform: UNKNOWN
